pmaudit/__init__.py
pmaudit/pmaudit
pmaudit/pmauditor.py
pmaudit/sys.pth
pmaudit-1.0.9.dist-info/LICENSE.md
pmaudit-1.0.9.dist-info/METADATA
pmaudit-1.0.9.dist-info/WHEEL
pmaudit-1.0.9.dist-info/top_level.txt
pmaudit-1.0.9.dist-info/RECORD
