Metadata-Version: 2.1
Name: pmaudit
Version: 1.0.9
Summary: Poor Man's File Auditor
Author-email: David Boyce <github@boyski.com>
License: GNU GENERAL PUBLIC LICENSE
Project-URL: Homepage, https://github.com/boyski/pmaudit
Project-URL: Bug Tracker, https://github.com/boyski/pmaudit/issues
Classifier: Programming Language :: Python :: 3
Classifier: License :: OSI Approved :: GNU General Public License v3 (GPLv3)
Classifier: Operating System :: OS Independent
Requires-Python: >=3.7
License-File: LICENSE.md
